liga/pytorch/__init__.py
liga/pytorch/codegen.py
liga/pytorch/pandas.py
liga/pytorch/transforms.py
liga/pytorch/models/__init__.py
liga/pytorch/models/convnext_base.py
liga/pytorch/models/convnext_large.py
liga/pytorch/models/convnext_small.py
liga/pytorch/models/convnext_tiny.py
liga/pytorch/models/efficientnet_b0.py
liga/pytorch/models/efficientnet_b1.py
liga/pytorch/models/efficientnet_b2.py
liga/pytorch/models/efficientnet_b3.py
liga/pytorch/models/efficientnet_b4.py
liga/pytorch/models/efficientnet_b5.py
liga/pytorch/models/efficientnet_b6.py
liga/pytorch/models/efficientnet_b7.py
liga/pytorch/models/fasterrcnn.py
liga/pytorch/models/fasterrcnn_mobilenet_v3_large_320_fpn.py
liga/pytorch/models/fasterrcnn_mobilenet_v3_large_fpn.py
liga/pytorch/models/fasterrcnn_resnet50_fpn.py
liga/pytorch/models/feature_extractor.py
liga/pytorch/models/keypointrcnn.py
liga/pytorch/models/maskrcnn.py
liga/pytorch/models/resnet101.py
liga/pytorch/models/resnet152.py
liga/pytorch/models/resnet18.py
liga/pytorch/models/resnet34.py
liga/pytorch/models/resnet50.py
liga/pytorch/models/retinanet.py
liga/pytorch/models/ssd.py
liga/pytorch/models/ssd_class_scores.py
liga/pytorch/models/ssdlite.py
liga/pytorch/models/torch.py
liga_tv-0.3.0.dist-info/METADATA
liga_tv-0.3.0.dist-info/WHEEL
liga_tv-0.3.0.dist-info/namespace_packages.txt
liga_tv-0.3.0.dist-info/top_level.txt
liga_tv-0.3.0.dist-info/RECORD
