Metadata-Version: 2.1
Name: liga-tv
Version: 0.3.0
Requires-Python: <3.10,>=3.8
Requires-Dist: ligavision (<0.4.0,>=0.3.0)
Requires-Dist: torchvision (>=0.11.3)
